LICENSE
MANIFEST.in
README.rst
setup.py
fountain/__init__.py
fountain/latex.py
fountain/main.py
fountain.egg-info/PKG-INFO
fountain.egg-info/SOURCES.txt
fountain.egg-info/dependency_links.txt
fountain.egg-info/entry_points.txt
fountain.egg-info/top_level.txt