Metadata-Version: 1.0
Name: fountain
Version: 0.1.2
Summary: Parses foutain screenplay markup
Home-page: bitbucket.org/gabriel.montagne/fountain
Author: gabriel montangé láscaris-comneno
Author-email: gabriel@tibas.london
License: MIT
Platform: any
